netbox_zabbix_zdluo/__init__.py
netbox_zabbix_zdluo-0.1.dist-info/METADATA
netbox_zabbix_zdluo-0.1.dist-info/WHEEL
netbox_zabbix_zdluo-0.1.dist-info/top_level.txt
netbox_zabbix_zdluo-0.1.dist-info/RECORD
