Metadata-Version: 2.1
Name: netbox-zabbix-zdluo
Version: 0.1
Summary: A description of your plugin
Home-page: UNKNOWN
Author: zdluo
Author-email: zdluo@glprop.com
License: UNKNOWN
Platform: UNKNOWN
